genexpressor/__init__.py
genexpressor/cli.py
genexpressor/runner.py
genexpressor/resources/deseq2_runner.R
genexpressor-0.1.7.dist-info/METADATA
genexpressor-0.1.7.dist-info/WHEEL
genexpressor-0.1.7.dist-info/entry_points.txt
genexpressor-0.1.7.dist-info/RECORD
