Metadata-Version: 2.4
Name: GeneXpressor
Version: 0.1.7
Summary: DESeq2 runner (Python + rpy2) for bulk RNA-seq with auto-discovery, E2E DE, plots, HTML report.
Project-URL: Homepage, https://github.com/shari01/GeneXpressor
Author-email: Sheryar Malik <sheryarmalik1403@gmail.com>
License: MIT
Keywords: DESeq2,RNA-seq,bioinformatics,differential-expression,rpy2
Classifier: License :: OSI Approved :: MIT License
Classifier: Operating System :: OS Independent
Classifier: Programming Language :: Python :: 3
Classifier: Programming Language :: Python :: 3 :: Only
Classifier: Topic :: Scientific/Engineering :: Bio-Informatics
Requires-Python: >=3.9
Requires-Dist: rpy2>=3.5
